{"mirroredOn":"2025-07-09T16:39:51.6334135+00:00","publishedOn":"2025-07-09T16:36:59+00:00","version":1,"publishedFiles":[{"fileName":"./pulumi-resource-grafana-v0.18.0-darwin-amd64.tar.gz","algo":"Sha1","source":"pulumi-grafana_0.18.0_checksums.txt","hash":"d13693a9b0c12166fe0571fc7d3566ec277136db"},{"fileName":"./pulumi-resource-grafana-v0.18.0-darwin-arm64.tar.gz","algo":"Sha1","source":"pulumi-grafana_0.18.0_checksums.txt","hash":"1c663c1d69cf051ccbdf3d585439331b183194fd"},{"fileName":"./pulumi-resource-grafana-v0.18.0-linux-amd64.tar.gz","algo":"Sha1","source":"pulumi-grafana_0.18.0_checksums.txt","hash":"516210fbf7bd3d7ea2cb559443175bb234086d3f"},{"fileName":"./pulumi-resource-grafana-v0.18.0-linux-arm64.tar.gz","algo":"Sha1","source":"pulumi-grafana_0.18.0_checksums.txt","hash":"6497fff09aa7a0123c022b3ad6e6703082f947e6"},{"fileName":"./pulumi-resource-grafana-v0.18.0-windows-amd64.tar.gz","algo":"Sha1","source":"pulumi-grafana_0.18.0_checksums.txt","hash":"39a439b856b9f3e6c86b15b635f43bb5ffcff21c"}]}