{"mirroredOn":"2026-07-09T17:13:43.8711456+00:00","publishedOn":"2026-07-09T17:12:17+00:00","version":1,"publishedFiles":[{"fileName":"terraform-provider-qovery_0.86.1_darwin_amd64.zip","algo":"Sha256","source":"terraform-provider-qovery_0.86.1_SHA256SUMS","hash":"9c88eea96d6ba92d8805340284358da949b02053174185125cb4108dc01fede2"},{"fileName":"terraform-provider-qovery_0.86.1_darwin_arm64.zip","algo":"Sha256","source":"terraform-provider-qovery_0.86.1_SHA256SUMS","hash":"0788f099733aa455067b4be0a5ab34a736379d2c399ddbcc79973e78cce775b7"},{"fileName":"terraform-provider-qovery_0.86.1_freebsd_386.zip","algo":"Sha256","source":"terraform-provider-qovery_0.86.1_SHA256SUMS","hash":"a7f02d1e0b6c1488f1796ee3feac44c734640d51bda8d61a9931a7371c6f9182"},{"fileName":"terraform-provider-qovery_0.86.1_freebsd_amd64.zip","algo":"Sha256","source":"terraform-provider-qovery_0.86.1_SHA256SUMS","hash":"9bf75bf040700e2a4c7b87a43dd98d8ded596c9ef5e1437c788c918fc7149c84"},{"fileName":"terraform-provider-qovery_0.86.1_freebsd_arm.zip","algo":"Sha256","source":"terraform-provider-qovery_0.86.1_SHA256SUMS","hash":"03f88d9c3d931738288632617bc46c8876c9d71dbd59423fc08a1288f081fd48"},{"fileName":"terraform-provider-qovery_0.86.1_freebsd_arm64.zip","algo":"Sha256","source":"terraform-provider-qovery_0.86.1_SHA256SUMS","hash":"7ef2df433885b17e08c285f5688daf40d99d5c97a556ec92c1b48f27a232df91"},{"fileName":"terraform-provider-qovery_0.86.1_linux_386.zip","algo":"Sha256","source":"terraform-provider-qovery_0.86.1_SHA256SUMS","hash":"8c1695c1167de354f2e2cf4cef82319ad088f303ed15a5cb825aceb27aebb6fa"},{"fileName":"terraform-provider-qovery_0.86.1_linux_amd64.zip","algo":"Sha256","source":"terraform-provider-qovery_0.86.1_SHA256SUMS","hash":"ab5c1a5022f55b95503af5b379a7cddca7ec964b91bb56d7c1930c0823f6078c"},{"fileName":"terraform-provider-qovery_0.86.1_linux_arm.zip","algo":"Sha256","source":"terraform-provider-qovery_0.86.1_SHA256SUMS","hash":"7e9c92cc96502e1e116c102067c69505d101eb821069908d91780663bf7fb0da"},{"fileName":"terraform-provider-qovery_0.86.1_linux_arm64.zip","algo":"Sha256","source":"terraform-provider-qovery_0.86.1_SHA256SUMS","hash":"6537b3d3efbae3edf6a07275d567df25b9b4cf5e09aeeb212949280201e7a9a5"},{"fileName":"terraform-provider-qovery_0.86.1_manifest.json","algo":"Sha256","source":"terraform-provider-qovery_0.86.1_SHA256SUMS","hash":"5974c92811f847819094fc2b0fb75e63fe9c403f1475732c9e882c29a325c917"},{"fileName":"terraform-provider-qovery_0.86.1_windows_386.zip","algo":"Sha256","source":"terraform-provider-qovery_0.86.1_SHA256SUMS","hash":"c82d1aefdfead887b8f2a14b74499534ec987fca44c9dc0b20686a3b42246f32"},{"fileName":"terraform-provider-qovery_0.86.1_windows_amd64.zip","algo":"Sha256","source":"terraform-provider-qovery_0.86.1_SHA256SUMS","hash":"d938978ea2818498b57faf320e60b3084a2b7db66c2a4798c9d64522e5676473"},{"fileName":"terraform-provider-qovery_0.86.1_windows_arm64.zip","algo":"Sha256","source":"terraform-provider-qovery_0.86.1_SHA256SUMS","hash":"d8d84f57671759308902278ef0ff486594ceac96149de390cd8adb6170f646a3"}]}