{"mirroredOn":"2026-05-28T03:41:33.5158499+00:00","publishedOn":"2026-05-28T03:39:41+00:00","version":1,"publishedFiles":[{"fileName":"tc2-hat-controller_0.29.0_arm64.deb","algo":"Sha256","source":"tc2-hat-controller_0.29.0_checksums.txt","hash":"a72d6487f0ad6826afa82bc02f0ab497e0efae74fb538257850cf57270f2d5e5"},{"fileName":"tc2-hat-controller_0.29.0_linux_arm64.tar.gz","algo":"Sha256","source":"tc2-hat-controller_0.29.0_checksums.txt","hash":"5672b093809a906eae3e19d491b6f36ca3005297ac444bb5e4e00737c09dc6ca"}]}