{"mirroredOn":"2025-04-29T11:02:45.4434022+00:00","publishedOn":"2025-04-29T10:56:21+00:00","version":1,"publishedFiles":[{"fileName":"terraform-provider-http2b64_1.0.8_darwin_amd64.zip","algo":"Sha256","source":"terraform-provider-http2b64_1.0.8_SHA256SUMS","hash":"a3b37a7746f306557bb45c66c514d66937dac91d23544316a106b925c9b48a18"},{"fileName":"terraform-provider-http2b64_1.0.8_darwin_arm64.zip","algo":"Sha256","source":"terraform-provider-http2b64_1.0.8_SHA256SUMS","hash":"fc2fb8f052f27acb417969f8ab884091b9b4a9be0934ab95e2f8fd522907c49c"},{"fileName":"terraform-provider-http2b64_1.0.8_freebsd_386.zip","algo":"Sha256","source":"terraform-provider-http2b64_1.0.8_SHA256SUMS","hash":"8deead074a5a199211f1869eab54feffd781cfe9b3a5c876a9a99373494c5cf8"},{"fileName":"terraform-provider-http2b64_1.0.8_freebsd_amd64.zip","algo":"Sha256","source":"terraform-provider-http2b64_1.0.8_SHA256SUMS","hash":"bbae2ce9e9b58f2ac8d33d443f06b1ff4ff46f91f7fa3d1cd97d1d0ce6cf8f9f"},{"fileName":"terraform-provider-http2b64_1.0.8_freebsd_arm.zip","algo":"Sha256","source":"terraform-provider-http2b64_1.0.8_SHA256SUMS","hash":"0d6150096483f4fd1a067513e0c1b393951fdda7a5ef7411c58fd5dfab8d5261"},{"fileName":"terraform-provider-http2b64_1.0.8_freebsd_arm64.zip","algo":"Sha256","source":"terraform-provider-http2b64_1.0.8_SHA256SUMS","hash":"e60a6c70b788f8c2ff67e5cd621dad7f82e01b4ac47663d15afa81be8bf6ed4c"},{"fileName":"terraform-provider-http2b64_1.0.8_linux_386.zip","algo":"Sha256","source":"terraform-provider-http2b64_1.0.8_SHA256SUMS","hash":"873f7288266908a11403ddd1cea6abd89361220cc157002fea4173f0e307b83d"},{"fileName":"terraform-provider-http2b64_1.0.8_linux_amd64.zip","algo":"Sha256","source":"terraform-provider-http2b64_1.0.8_SHA256SUMS","hash":"09469654ae748dc190a9891562e8d15bb621b2c6ec214f3a579c4c81c784db69"},{"fileName":"terraform-provider-http2b64_1.0.8_linux_arm.zip","algo":"Sha256","source":"terraform-provider-http2b64_1.0.8_SHA256SUMS","hash":"3e3daec90150b9d0b73ab03d6bea4da6476b4ddd4cc94d144d4931914e7ee59c"},{"fileName":"terraform-provider-http2b64_1.0.8_linux_arm64.zip","algo":"Sha256","source":"terraform-provider-http2b64_1.0.8_SHA256SUMS","hash":"7b9f65137802b2c9ade01b95e0a09d0ed80e9cecf23d1add5c407974d30971aa"},{"fileName":"terraform-provider-http2b64_1.0.8_manifest.json","algo":"Sha256","source":"terraform-provider-http2b64_1.0.8_SHA256SUMS","hash":"8bc8f61e496e96c81c46e1aa59bf2155b6acc80db1ea462f2ddd665748fcda7f"},{"fileName":"terraform-provider-http2b64_1.0.8_windows_386.zip","algo":"Sha256","source":"terraform-provider-http2b64_1.0.8_SHA256SUMS","hash":"13d37bd95c38e94d42d367e74d0b509e0c2a441e59f805e46ce728e162173615"},{"fileName":"terraform-provider-http2b64_1.0.8_windows_amd64.zip","algo":"Sha256","source":"terraform-provider-http2b64_1.0.8_SHA256SUMS","hash":"ac24c762adbe43d6cfe8ba82703a8819565435ce77f60522e42ff5d876be39ec"},{"fileName":"terraform-provider-http2b64_1.0.8_windows_arm.zip","algo":"Sha256","source":"terraform-provider-http2b64_1.0.8_SHA256SUMS","hash":"251746ad8058d01f76e95bf15757c68de1cb8fa0a66e5fb38045582007374be2"},{"fileName":"terraform-provider-http2b64_1.0.8_windows_arm64.zip","algo":"Sha256","source":"terraform-provider-http2b64_1.0.8_SHA256SUMS","hash":"cc484224cd0c75d8e17c9255cf14eebd3d1cfd97a725b3d855cd0536491c7f05"}]}