{"mirroredOn":"2025-12-15T07:44:42.4873086+00:00","publishedOn":"2025-12-15T07:43:13+00:00","version":1,"publishedFiles":[{"fileName":"terraform-provider-meshstack_0.16.0_darwin_amd64.zip","algo":"Sha256","source":"terraform-provider-meshstack_0.16.0_SHA256SUMS","hash":"19d47cb933607b02c3030b83df66b3ded21c3bfc78d6eb72f9731a9431bef1d2"},{"fileName":"terraform-provider-meshstack_0.16.0_darwin_arm64.zip","algo":"Sha256","source":"terraform-provider-meshstack_0.16.0_SHA256SUMS","hash":"f00a5f8cd40a9813e19a112e164c3f8a0b9a6ad94de317c61ce6a1777efa2d6f"},{"fileName":"terraform-provider-meshstack_0.16.0_freebsd_386.zip","algo":"Sha256","source":"terraform-provider-meshstack_0.16.0_SHA256SUMS","hash":"a3a930b417a82b411684c7cf45405cb9d60a67d36deb62d0948b05a534633b72"},{"fileName":"terraform-provider-meshstack_0.16.0_freebsd_amd64.zip","algo":"Sha256","source":"terraform-provider-meshstack_0.16.0_SHA256SUMS","hash":"1bc53d53a7a95e4271a179f8b01f22526b19f24b38e079db63002a35e9c182f5"},{"fileName":"terraform-provider-meshstack_0.16.0_freebsd_arm.zip","algo":"Sha256","source":"terraform-provider-meshstack_0.16.0_SHA256SUMS","hash":"1aeb5f5f3b53872cf56ea3667274fb35029962050701cebb92925d1798ce7514"},{"fileName":"terraform-provider-meshstack_0.16.0_freebsd_arm64.zip","algo":"Sha256","source":"terraform-provider-meshstack_0.16.0_SHA256SUMS","hash":"469842d37264d44f33a97fcf497bbeb4708315589509fcff2cb03bad092d12f9"},{"fileName":"terraform-provider-meshstack_0.16.0_linux_386.zip","algo":"Sha256","source":"terraform-provider-meshstack_0.16.0_SHA256SUMS","hash":"9306abe56cd92bf10a027294785ed71ba43b28f9d1cdf84b170c75d4b29c7e22"},{"fileName":"terraform-provider-meshstack_0.16.0_linux_amd64.zip","algo":"Sha256","source":"terraform-provider-meshstack_0.16.0_SHA256SUMS","hash":"80ef84b338252ff88ea19d5246dbac8da9c5ea290d0c626d22b3a604e4fcf880"},{"fileName":"terraform-provider-meshstack_0.16.0_linux_arm.zip","algo":"Sha256","source":"terraform-provider-meshstack_0.16.0_SHA256SUMS","hash":"baa0091f41b1b069c96e53712017bab5c3bc7b47c4a5106ef3977e869c07e88e"},{"fileName":"terraform-provider-meshstack_0.16.0_linux_arm64.zip","algo":"Sha256","source":"terraform-provider-meshstack_0.16.0_SHA256SUMS","hash":"da4e7c4bb90f4e7958c3f879028a66cb6ac3afe6ae404083b5be2400cf3c94d7"},{"fileName":"terraform-provider-meshstack_0.16.0_manifest.json","algo":"Sha256","source":"terraform-provider-meshstack_0.16.0_SHA256SUMS","hash":"890df766e9b839623b1f0437355032a3c006226a6c200cd911e15ee1a9014e9f"},{"fileName":"terraform-provider-meshstack_0.16.0_windows_386.zip","algo":"Sha256","source":"terraform-provider-meshstack_0.16.0_SHA256SUMS","hash":"698e6e50a837325fce4d5b394fd413e81c8b2848c0ec7aceb470ac3983b644b1"},{"fileName":"terraform-provider-meshstack_0.16.0_windows_amd64.zip","algo":"Sha256","source":"terraform-provider-meshstack_0.16.0_SHA256SUMS","hash":"d520c55b46fd384f06a4b080a377ba43cef9f78bf512bcf089bae9ec230d1fe5"},{"fileName":"terraform-provider-meshstack_0.16.0_windows_arm.zip","algo":"Sha256","source":"terraform-provider-meshstack_0.16.0_SHA256SUMS","hash":"e90cd52092dfedf5469536d92f71c421df45ac8fbdc44ccad024329ba2b8a4a2"},{"fileName":"terraform-provider-meshstack_0.16.0_windows_arm64.zip","algo":"Sha256","source":"terraform-provider-meshstack_0.16.0_SHA256SUMS","hash":"d2256a3cd8bc432194471bbac51fb781547a8c1240232f8c4b470de1abd02607"}]}