{"mirroredOn":"2025-12-18T19:23:45.1199286+00:00","publishedOn":"2025-12-18T19:22:22+00:00","version":1,"publishedFiles":[{"fileName":"./pulumi-resource-xyz-v1.1.338-darwin-amd64.tar.gz","algo":"Sha1","source":"pulumi-xyz_1.1.338_checksums.txt","hash":"e43bc5bd06743f5441b994cf9f0341ddbdfa61be"},{"fileName":"./pulumi-resource-xyz-v1.1.338-darwin-arm64.tar.gz","algo":"Sha1","source":"pulumi-xyz_1.1.338_checksums.txt","hash":"0fc7f8b6a61bbb5fe148185a740a6f4c9988cbdc"},{"fileName":"./pulumi-resource-xyz-v1.1.338-linux-amd64.tar.gz","algo":"Sha1","source":"pulumi-xyz_1.1.338_checksums.txt","hash":"75739adf35babf53bb7f5d6985718475d63e86ff"},{"fileName":"./pulumi-resource-xyz-v1.1.338-linux-arm64.tar.gz","algo":"Sha1","source":"pulumi-xyz_1.1.338_checksums.txt","hash":"416bda27f5cd2d78f97e69ee0f29b2e7edbe24ff"},{"fileName":"./pulumi-resource-xyz-v1.1.338-windows-amd64.tar.gz","algo":"Sha1","source":"pulumi-xyz_1.1.338_checksums.txt","hash":"6d080ea2d2c23f8c9e939247aff26358462755cb"},{"fileName":"./pulumi-resource-xyz-v1.1.338-windows-arm64.tar.gz","algo":"Sha1","source":"pulumi-xyz_1.1.338_checksums.txt","hash":"5978b3b8f9929c447dc71c1d9f401b2db1079803"}]}