{"mirroredOn":"2025-05-29T19:16:53.0445697+00:00","publishedOn":"2025-05-29T19:13:15+00:00","version":1,"publishedFiles":[{"fileName":"linkerd2-cli-edge-25.5.5-linux-amd64","algo":"Sha256","source":"linkerd2-cli-edge-25.5.5-linux-amd64.sha256","hash":"0496643692f69236eadc241979142ce9bb483cacfb16c2d5548e21b47df1dd9a"},{"fileName":"linkerd2-cli-edge-25.5.5-darwin","algo":"Sha256","source":"linkerd2-cli-edge-25.5.5-darwin.sha256","hash":"6d39cf4f9c930c2d42a1c76cba657cfd1c84b1d4eef1b1d715a4fbca71c8e627"},{"fileName":"linkerd2-cli-edge-25.5.5-linux-arm","algo":"Sha256","source":"linkerd2-cli-edge-25.5.5-linux-arm.sha256","hash":"29b151b13b0f8a5b7264c4342b0f79e8f02ade0a80215ec29d8a177c8144b21d"},{"fileName":"linkerd2-cli-edge-25.5.5-darwin-arm64","algo":"Sha256","source":"linkerd2-cli-edge-25.5.5-darwin-arm64.sha256","hash":"1ef464c654d5a90b5ea8de48eb2ca3051542eac505e559db405d7a1b5f288e37"},{"fileName":"linkerd2-cli-edge-25.5.5-linux-arm64","algo":"Sha256","source":"linkerd2-cli-edge-25.5.5-linux-arm64.sha256","hash":"c550438398fa6467739106dc2f580b30ce34607bf18907e99043ce56b4f3a1fe"},{"fileName":"linkerd2-cli-edge-25.5.5-windows.exe","algo":"Sha256","source":"linkerd2-cli-edge-25.5.5-windows.exe.sha256","hash":"78e563a5e9d9db58215dac2e3e59b107672c5943e7a774a78f8163bb590fc234"}]}