{"mirroredOn":"2026-03-19T15:51:28.6517524+00:00","publishedOn":"2026-03-19T15:48:43+00:00","version":1,"publishedFiles":[{"fileName":"./pulumi-resource-oci-v4.3.1-darwin-amd64.tar.gz","algo":"Sha1","source":"pulumi-oci_4.3.1_checksums.txt","hash":"a96a4d02618261d01ff39cdeae7ce1546468f559"},{"fileName":"./pulumi-resource-oci-v4.3.1-darwin-arm64.tar.gz","algo":"Sha1","source":"pulumi-oci_4.3.1_checksums.txt","hash":"2f9abb49350347e684b616f52413242dbf9f16e2"},{"fileName":"./pulumi-resource-oci-v4.3.1-linux-amd64.tar.gz","algo":"Sha1","source":"pulumi-oci_4.3.1_checksums.txt","hash":"de4d1d601d5f3bce27ed64758b7a1934ad9ca41c"},{"fileName":"./pulumi-resource-oci-v4.3.1-linux-arm64.tar.gz","algo":"Sha1","source":"pulumi-oci_4.3.1_checksums.txt","hash":"307b2155590dafb584d116931ab4616ad3e99243"},{"fileName":"./pulumi-resource-oci-v4.3.1-windows-amd64.tar.gz","algo":"Sha1","source":"pulumi-oci_4.3.1_checksums.txt","hash":"601351d156367d56ee8b6ec97778f6612ae35031"},{"fileName":"./pulumi-resource-oci-v4.3.1-windows-arm64.tar.gz","algo":"Sha1","source":"pulumi-oci_4.3.1_checksums.txt","hash":"2fdeffdb580267fd9cd26aff2bfd2e09e7053bf1"}]}