{"mirroredOn":"2024-12-23T21:25:45.2258359+00:00","publishedOn":"2024-12-21T00:48:41+00:00","version":1,"publishedFiles":[{"fileName":"./pulumi-resource-akamai-v7.6.1-darwin-amd64.tar.gz","algo":"Sha1","source":"pulumi-akamai_7.6.1_checksums.txt","hash":"6b2a08e129cd88fefbb43d4f80870b31ca9b43d8"},{"fileName":"./pulumi-resource-akamai-v7.6.1-darwin-arm64.tar.gz","algo":"Sha1","source":"pulumi-akamai_7.6.1_checksums.txt","hash":"abe9b02a728811465397f6e1de3f9def78f17121"},{"fileName":"./pulumi-resource-akamai-v7.6.1-linux-amd64.tar.gz","algo":"Sha1","source":"pulumi-akamai_7.6.1_checksums.txt","hash":"48fce0416d441701dbc53360273543d84d6d80ef"},{"fileName":"./pulumi-resource-akamai-v7.6.1-linux-arm64.tar.gz","algo":"Sha1","source":"pulumi-akamai_7.6.1_checksums.txt","hash":"5cd60cbcc71d667be1686f73353da6daa405a3e2"},{"fileName":"./pulumi-resource-akamai-v7.6.1-windows-amd64.tar.gz","algo":"Sha1","source":"pulumi-akamai_7.6.1_checksums.txt","hash":"c079a3beede6fa3f23df2a897b7af2cdd263d3ff"}]}