{"mirroredOn":"2025-06-19T03:56:14.5051461+00:00","publishedOn":"2025-06-19T03:54:53+00:00","version":1,"publishedFiles":[{"fileName":"./pulumi-resource-artifactory-v8.8.5-darwin-amd64.tar.gz","algo":"Sha1","source":"pulumi-artifactory_8.8.5_checksums.txt","hash":"03aa27826dad468c45b8de7ce3aebb57550044a9"},{"fileName":"./pulumi-resource-artifactory-v8.8.5-darwin-arm64.tar.gz","algo":"Sha1","source":"pulumi-artifactory_8.8.5_checksums.txt","hash":"800abc7f7246d96f265eed7f0ff118abe70d2275"},{"fileName":"./pulumi-resource-artifactory-v8.8.5-linux-amd64.tar.gz","algo":"Sha1","source":"pulumi-artifactory_8.8.5_checksums.txt","hash":"d4495fd96445df7589d6d6ed24e33db21aefbc6b"},{"fileName":"./pulumi-resource-artifactory-v8.8.5-linux-arm64.tar.gz","algo":"Sha1","source":"pulumi-artifactory_8.8.5_checksums.txt","hash":"6633674b8cafca75e533a4308aa64c0e359501d7"},{"fileName":"./pulumi-resource-artifactory-v8.8.5-windows-amd64.tar.gz","algo":"Sha1","source":"pulumi-artifactory_8.8.5_checksums.txt","hash":"8e0643ef9ae13ff090679419d4f6263c0114983e"}]}