{"mirroredOn":"2025-10-13T06:41:20.8254717+00:00","publishedOn":"2025-10-13T06:39:47+00:00","version":1,"publishedFiles":[{"fileName":"quantus-node-v0.2.9-aarch64-apple-darwin.tar.gz","algo":"Sha256","source":"sha256sums-v0.2.9-aarch64-apple-darwin.txt","hash":"366e10f415ec6bbfa06a0ffcfef8fc5a31ff2d50394c2e7503698b03f144c373"},{"fileName":"quantus-node-v0.2.9-x86_64-pc-windows-msvc.zip","algo":"Sha256","source":"sha256sums-v0.2.9-x86_64-pc-windows-msvc.txt","hash":"5bce40276d0b4d6b40d1ee6c6dabb1236c5bcbd7f2ef3689c549510e88802600"},{"fileName":"quantus-node-v0.2.9-x86_64-unknown-linux-gnu.tar.gz","algo":"Sha256","source":"sha256sums-v0.2.9-x86_64-unknown-linux-gnu.txt","hash":"89a185b94954254680884a4b3115743d65529bd40f9b0afe4e2fefcb3d2c4de2"}]}