{"mirroredOn":"2025-11-26T17:56:36.2290822+00:00","publishedOn":"2025-11-26T17:54:38+00:00","version":1,"publishedFiles":[{"fileName":"terraform-provider-cpln_1.2.17_darwin_amd64.zip","algo":"Sha256","source":"terraform-provider-cpln_1.2.17_SHA256SUMS","hash":"b6d2f50f1d9a8f76096b3d51f61a4b35793ecd1a1d262429b9105805e71f1954"},{"fileName":"terraform-provider-cpln_1.2.17_darwin_arm64.zip","algo":"Sha256","source":"terraform-provider-cpln_1.2.17_SHA256SUMS","hash":"cf6fbd11655732f33254309e79286d3aaa64ef273f84882c23f0e5deb48bcb0b"},{"fileName":"terraform-provider-cpln_1.2.17_freebsd_386.zip","algo":"Sha256","source":"terraform-provider-cpln_1.2.17_SHA256SUMS","hash":"5907e062f1ec535cc572932b08c5be5b92ed9ee03a71883a6c384328a011fa61"},{"fileName":"terraform-provider-cpln_1.2.17_freebsd_amd64.zip","algo":"Sha256","source":"terraform-provider-cpln_1.2.17_SHA256SUMS","hash":"7fd5191893053cb5708c7cd349982dd7f99c04b74d9a5e84f8fa38af910bf983"},{"fileName":"terraform-provider-cpln_1.2.17_freebsd_arm.zip","algo":"Sha256","source":"terraform-provider-cpln_1.2.17_SHA256SUMS","hash":"49d6608fdcee144fd4457dfa2203b29068a1d88bbf2b0ce7f7de107ea78d5dc9"},{"fileName":"terraform-provider-cpln_1.2.17_freebsd_arm64.zip","algo":"Sha256","source":"terraform-provider-cpln_1.2.17_SHA256SUMS","hash":"4f70a6e832bfc3a71c96bc6ba599d479c40f66e340beb0d5226651dda50def9d"},{"fileName":"terraform-provider-cpln_1.2.17_linux_386.zip","algo":"Sha256","source":"terraform-provider-cpln_1.2.17_SHA256SUMS","hash":"efde9fd197eae45ddc52f0811cc6b32c1c32113d96c00081a4d2cd02ebd322f4"},{"fileName":"terraform-provider-cpln_1.2.17_linux_amd64.zip","algo":"Sha256","source":"terraform-provider-cpln_1.2.17_SHA256SUMS","hash":"2119d4302a16e83f8b117983a5661222013793f66ac77c23925ca3df94672f5e"},{"fileName":"terraform-provider-cpln_1.2.17_linux_arm.zip","algo":"Sha256","source":"terraform-provider-cpln_1.2.17_SHA256SUMS","hash":"4991abd2eba4496ed37db792d46ec2089bf2322565599504a6c306c5671e088e"},{"fileName":"terraform-provider-cpln_1.2.17_linux_arm64.zip","algo":"Sha256","source":"terraform-provider-cpln_1.2.17_SHA256SUMS","hash":"31ccfff7d7be6da279fc83dd04090ee9f136e25c384f751bf74511f783e14c2c"},{"fileName":"terraform-provider-cpln_1.2.17_manifest.json","algo":"Sha256","source":"terraform-provider-cpln_1.2.17_SHA256SUMS","hash":"f809ab383cca0a5f83072981c64208cbd7fa67e986a86ee02dd2c82333221e32"},{"fileName":"terraform-provider-cpln_1.2.17_windows_386.zip","algo":"Sha256","source":"terraform-provider-cpln_1.2.17_SHA256SUMS","hash":"46497ae3a5ec5477762ae0fbdc9f443ef30726bf4712eb276cea1d78d42531ab"},{"fileName":"terraform-provider-cpln_1.2.17_windows_amd64.zip","algo":"Sha256","source":"terraform-provider-cpln_1.2.17_SHA256SUMS","hash":"60e421796999e89b79a35b1b784fc72d1270dcd516ff92b8b4900b3eb683bb46"},{"fileName":"terraform-provider-cpln_1.2.17_windows_arm.zip","algo":"Sha256","source":"terraform-provider-cpln_1.2.17_SHA256SUMS","hash":"56719561cced35adcb5a51ef1f129f6247f31c1ce5a67c1b9e1cec6f801386ea"},{"fileName":"terraform-provider-cpln_1.2.17_windows_arm64.zip","algo":"Sha256","source":"terraform-provider-cpln_1.2.17_SHA256SUMS","hash":"645c4f074660f68a5c8588552e91733213789d6ec4f37fad6eb321153d80f218"}]}