{"mirroredOn":"2026-02-12T09:57:31.1700677+00:00","publishedOn":"2026-02-12T09:54:39+00:00","version":1,"publishedFiles":[{"fileName":"terraform-provider-bunnynet_0.13.0_darwin_amd64.zip","algo":"Sha256","source":"terraform-provider-bunnynet_0.13.0_SHA256SUMS","hash":"923d3b2b187a8a86b2529aaf2665259c3488d14d7841071ae0ff4543bac0e0e7"},{"fileName":"terraform-provider-bunnynet_0.13.0_darwin_arm64.zip","algo":"Sha256","source":"terraform-provider-bunnynet_0.13.0_SHA256SUMS","hash":"35030e863ccd090c0341a4f73eda9f45edd5c0242b900a46877ea723e666d565"},{"fileName":"terraform-provider-bunnynet_0.13.0_freebsd_386.zip","algo":"Sha256","source":"terraform-provider-bunnynet_0.13.0_SHA256SUMS","hash":"f6a71ae77dd33998e9ccecde2ba5ff9cde51f925d36d9474d2922d17d45a91e9"},{"fileName":"terraform-provider-bunnynet_0.13.0_freebsd_amd64.zip","algo":"Sha256","source":"terraform-provider-bunnynet_0.13.0_SHA256SUMS","hash":"a30ef52d964da31faa730eac825e6852e29c5b1cad9ea8dd01119da764d45e3d"},{"fileName":"terraform-provider-bunnynet_0.13.0_freebsd_arm.zip","algo":"Sha256","source":"terraform-provider-bunnynet_0.13.0_SHA256SUMS","hash":"a1768322292652ab94cf06bdbb9bb47ae94174ddfec45d2d335d34474c03fdb8"},{"fileName":"terraform-provider-bunnynet_0.13.0_freebsd_arm64.zip","algo":"Sha256","source":"terraform-provider-bunnynet_0.13.0_SHA256SUMS","hash":"bd71461020a7c50a4b872b56653f1f27e3a2f57c0cf2e7ff7de4fde95565424a"},{"fileName":"terraform-provider-bunnynet_0.13.0_linux_386.zip","algo":"Sha256","source":"terraform-provider-bunnynet_0.13.0_SHA256SUMS","hash":"013309bf0abb280c20ad49c682a1f4bf8467b67fe683181ed01d8fbd844f052e"},{"fileName":"terraform-provider-bunnynet_0.13.0_linux_amd64.zip","algo":"Sha256","source":"terraform-provider-bunnynet_0.13.0_SHA256SUMS","hash":"442e2f33cef96ad20db30cd8de04b91d4f26729645411cfe4f80a2ed8341ca66"},{"fileName":"terraform-provider-bunnynet_0.13.0_linux_arm.zip","algo":"Sha256","source":"terraform-provider-bunnynet_0.13.0_SHA256SUMS","hash":"e9acfa913a5fdbfa774f1c686cf33cf77d12b9ce7ed51d64f58a2e8aaf3b1e67"},{"fileName":"terraform-provider-bunnynet_0.13.0_linux_arm64.zip","algo":"Sha256","source":"terraform-provider-bunnynet_0.13.0_SHA256SUMS","hash":"6ad307bd027c2939e6197e98214c6bfd8ab6d5072c261669e9fdcbe876ec675a"},{"fileName":"terraform-provider-bunnynet_0.13.0_manifest.json","algo":"Sha256","source":"terraform-provider-bunnynet_0.13.0_SHA256SUMS","hash":"890df766e9b839623b1f0437355032a3c006226a6c200cd911e15ee1a9014e9f"},{"fileName":"terraform-provider-bunnynet_0.13.0_openbsd_386.zip","algo":"Sha256","source":"terraform-provider-bunnynet_0.13.0_SHA256SUMS","hash":"c3552bc1b8d32c5fb81478e44b4477cbbc386ac1acd24bf4927bdd62bc732bca"},{"fileName":"terraform-provider-bunnynet_0.13.0_openbsd_amd64.zip","algo":"Sha256","source":"terraform-provider-bunnynet_0.13.0_SHA256SUMS","hash":"99505c2cdf1ce4e0e7fe862278c8174716538d33ffc82b37bca9e204a6b0f5e6"},{"fileName":"terraform-provider-bunnynet_0.13.0_openbsd_arm.zip","algo":"Sha256","source":"terraform-provider-bunnynet_0.13.0_SHA256SUMS","hash":"33585138055a2862bf8f061d1281d7054d2a9ae69747de4947e35de599a54bd8"},{"fileName":"terraform-provider-bunnynet_0.13.0_openbsd_arm64.zip","algo":"Sha256","source":"terraform-provider-bunnynet_0.13.0_SHA256SUMS","hash":"c79d761ec30b7d5c45bccde71a5ba5ab9b4974b76364c88898baf03c6cb4f720"},{"fileName":"terraform-provider-bunnynet_0.13.0_windows_386.zip","algo":"Sha256","source":"terraform-provider-bunnynet_0.13.0_SHA256SUMS","hash":"10549d4bdc922c2b350c11cea262edd48669cdc34a836d94d794684a86f9bdd5"},{"fileName":"terraform-provider-bunnynet_0.13.0_windows_amd64.zip","algo":"Sha256","source":"terraform-provider-bunnynet_0.13.0_SHA256SUMS","hash":"0016d8db546b1586f46ca6d824fd45fbb3d3459ae753106c0f12eb9ecbbf719f"},{"fileName":"terraform-provider-bunnynet_0.13.0_windows_arm.zip","algo":"Sha256","source":"terraform-provider-bunnynet_0.13.0_SHA256SUMS","hash":"03bfaaba5b2597d65ea36d813f92b617c50a32497a021879af63bcc1fd93b0f5"},{"fileName":"terraform-provider-bunnynet_0.13.0_windows_arm64.zip","algo":"Sha256","source":"terraform-provider-bunnynet_0.13.0_SHA256SUMS","hash":"c83eba097637a1ad49529d129d5886b64e148d457c6c5a55f45d1aebf405b55b"}]}