{"mirroredOn":"2025-05-12T20:10:21.6094871+00:00","publishedOn":"2025-05-12T20:08:52+00:00","version":1,"publishedFiles":[{"fileName":"terraform-provider-opslevel_1.4.1_darwin_amd64.zip","algo":"Sha256","source":"terraform-provider-opslevel_1.4.1_SHA256SUMS","hash":"9c024791181ce5745745952c1da1dc839712fab279fd347ce26d51c80e28faa3"},{"fileName":"terraform-provider-opslevel_1.4.1_darwin_arm64.zip","algo":"Sha256","source":"terraform-provider-opslevel_1.4.1_SHA256SUMS","hash":"6c70c6390af74b95e7df992945ad8d5f2f08f8b3c6cf84d0b6fb02625a0c5a97"},{"fileName":"terraform-provider-opslevel_1.4.1_freebsd_386.zip","algo":"Sha256","source":"terraform-provider-opslevel_1.4.1_SHA256SUMS","hash":"72fda06797135400539d63ac3cf716660e93ad958194a84ec075227b7f48314a"},{"fileName":"terraform-provider-opslevel_1.4.1_freebsd_amd64.zip","algo":"Sha256","source":"terraform-provider-opslevel_1.4.1_SHA256SUMS","hash":"81c03f2a5d84280a5227364bc212b5504568f335e28f536ffc8e12602e68c5ab"},{"fileName":"terraform-provider-opslevel_1.4.1_freebsd_arm.zip","algo":"Sha256","source":"terraform-provider-opslevel_1.4.1_SHA256SUMS","hash":"e422566995f6518260c2c2200e43058347d828c990f86e9523e17631fdc7dcd9"},{"fileName":"terraform-provider-opslevel_1.4.1_freebsd_arm64.zip","algo":"Sha256","source":"terraform-provider-opslevel_1.4.1_SHA256SUMS","hash":"d9d39ca4acb33fc62005ffe1c81df8f75e0acd51660ae7bba29d9ccefad74f95"},{"fileName":"terraform-provider-opslevel_1.4.1_linux_386.zip","algo":"Sha256","source":"terraform-provider-opslevel_1.4.1_SHA256SUMS","hash":"fc0a472a24ac23834215028041bb5b7af5af0dce72d30776cb150fe8abcb08d4"},{"fileName":"terraform-provider-opslevel_1.4.1_linux_amd64.zip","algo":"Sha256","source":"terraform-provider-opslevel_1.4.1_SHA256SUMS","hash":"ec6a3f60bba3ee32beb80c6bf38888dec0d15c312c40dcd326f2e9d6a00f3369"},{"fileName":"terraform-provider-opslevel_1.4.1_linux_arm.zip","algo":"Sha256","source":"terraform-provider-opslevel_1.4.1_SHA256SUMS","hash":"fd7f2b5e4ee3b3e9f99882f532765f827b7fa8f19c63663d12c5cd6e2560463e"},{"fileName":"terraform-provider-opslevel_1.4.1_linux_arm64.zip","algo":"Sha256","source":"terraform-provider-opslevel_1.4.1_SHA256SUMS","hash":"c985b1cde4404eca2edfdcac47269e1073bcb69dd88ad63c3f076b9fa38654c9"},{"fileName":"terraform-provider-opslevel_1.4.1_windows_386.zip","algo":"Sha256","source":"terraform-provider-opslevel_1.4.1_SHA256SUMS","hash":"5fda714735cefef9cc47afbc6d266749e9bcf19b025ce167af287f13d5eb88f8"},{"fileName":"terraform-provider-opslevel_1.4.1_windows_amd64.zip","algo":"Sha256","source":"terraform-provider-opslevel_1.4.1_SHA256SUMS","hash":"aa848f4c50e3aa63bb974d6bcf617b4edb3495be7352adbeb316bc6793e4edb3"},{"fileName":"terraform-provider-opslevel_1.4.1_windows_arm.zip","algo":"Sha256","source":"terraform-provider-opslevel_1.4.1_SHA256SUMS","hash":"f1e1ce44f860a1d9ad17bf43649f6d7a280f2979c6914e087c0915016903b46d"},{"fileName":"terraform-provider-opslevel_1.4.1_windows_arm64.zip","algo":"Sha256","source":"terraform-provider-opslevel_1.4.1_SHA256SUMS","hash":"353db97d2d5b98fe9750f9e848d5186b3ed6f22cf14735c96571ed633ede71eb"}]}