{"mirroredOn":"2026-05-22T15:23:17.7492791+00:00","publishedOn":"2026-05-22T15:21:14+00:00","version":1,"publishedFiles":[{"fileName":"./pulumi-resource-cloudflare-v6.17.0-darwin-amd64.tar.gz","algo":"Sha1","source":"pulumi-cloudflare_6.17.0_checksums.txt","hash":"de2e9ea0e89982e6bc6b3e49120bd23c6c07ecb9"},{"fileName":"./pulumi-resource-cloudflare-v6.17.0-darwin-arm64.tar.gz","algo":"Sha1","source":"pulumi-cloudflare_6.17.0_checksums.txt","hash":"7faaaa8b1bcd3c78d57dce64561272fce40e35c4"},{"fileName":"./pulumi-resource-cloudflare-v6.17.0-linux-amd64.tar.gz","algo":"Sha1","source":"pulumi-cloudflare_6.17.0_checksums.txt","hash":"fc14661a25dc62e3819bf026b8682e2a9d4b804e"},{"fileName":"./pulumi-resource-cloudflare-v6.17.0-linux-arm64.tar.gz","algo":"Sha1","source":"pulumi-cloudflare_6.17.0_checksums.txt","hash":"52595bd72375404a6045cbebb2c972148b1273fe"},{"fileName":"./pulumi-resource-cloudflare-v6.17.0-windows-amd64.tar.gz","algo":"Sha1","source":"pulumi-cloudflare_6.17.0_checksums.txt","hash":"5681b1376c6d9d539780900b1903f978b88bf01c"},{"fileName":"./pulumi-resource-cloudflare-v6.17.0-windows-arm64.tar.gz","algo":"Sha1","source":"pulumi-cloudflare_6.17.0_checksums.txt","hash":"bc39b803123d0a670a59cf95d06863ce2f76ff3a"}]}