{"mirroredOn":"2025-03-07T16:18:50.6342527+00:00","publishedOn":"2025-03-07T16:17:15+00:00","version":1,"publishedFiles":[{"fileName":"terraform-provider-gcore_0.14.0_darwin_amd64.zip","algo":"Sha256","source":"terraform-provider-gcore_0.14.0_SHA256SUMS","hash":"0fbf402ee586c501bbde42757b06e4973de9956018497a176de4e8c7600f0b5a"},{"fileName":"terraform-provider-gcore_0.14.0_darwin_arm64.zip","algo":"Sha256","source":"terraform-provider-gcore_0.14.0_SHA256SUMS","hash":"f1185af742366714527b6a8fce1000f10f87006e37c2349613c0fdeaf77d1a47"},{"fileName":"terraform-provider-gcore_0.14.0_linux_386.zip","algo":"Sha256","source":"terraform-provider-gcore_0.14.0_SHA256SUMS","hash":"1d28413c6710077b67c4af483c65b0888283a494dd9860a82a5fbb3086a50ab7"},{"fileName":"terraform-provider-gcore_0.14.0_linux_amd64.zip","algo":"Sha256","source":"terraform-provider-gcore_0.14.0_SHA256SUMS","hash":"7fb2f1445ef99c375254b5e4269de4dc943c01026e98aebb363683778173b2c8"},{"fileName":"terraform-provider-gcore_0.14.0_linux_arm.zip","algo":"Sha256","source":"terraform-provider-gcore_0.14.0_SHA256SUMS","hash":"2886a37dd919a30bc16fcfe9ce10d9b6a0444d261500dddeed6994edd466ba41"},{"fileName":"terraform-provider-gcore_0.14.0_linux_arm64.zip","algo":"Sha256","source":"terraform-provider-gcore_0.14.0_SHA256SUMS","hash":"2c3398713504d5b76bfda3daff8811ccf2d4b9234ab5991281c836774405808e"},{"fileName":"terraform-provider-gcore_0.14.0_manifest.json","algo":"Sha256","source":"terraform-provider-gcore_0.14.0_SHA256SUMS","hash":"f569b65999264a9416862bca5cd2a6177d94ccb0424f3a4ef424428912b9cb3c"},{"fileName":"terraform-provider-gcore_0.14.0_windows_386.zip","algo":"Sha256","source":"terraform-provider-gcore_0.14.0_SHA256SUMS","hash":"ce3fe5904a23480d1e365168574bd6eeae017f78c90a53d6637f225af726be35"},{"fileName":"terraform-provider-gcore_0.14.0_windows_amd64.zip","algo":"Sha256","source":"terraform-provider-gcore_0.14.0_SHA256SUMS","hash":"ee64e45c8f3fa7f71d5675d10bf83e2289c5b42fcffc1405ddb906b835666432"},{"fileName":"terraform-provider-gcore_0.14.0_windows_arm.zip","algo":"Sha256","source":"terraform-provider-gcore_0.14.0_SHA256SUMS","hash":"bca7be8456ebb39e2d148fcdd025ef19bc49105d0862e2f1b357a2fcc057b28c"},{"fileName":"terraform-provider-gcore_0.14.0_windows_arm64.zip","algo":"Sha256","source":"terraform-provider-gcore_0.14.0_SHA256SUMS","hash":"3d43cef9b3b822847e2a033839f60799369e216fd1efae5aa685cced07b57994"}]}