{"mirroredOn":"2025-08-19T17:15:20.215668+00:00","publishedOn":"2025-08-19T17:14:10+00:00","version":1,"publishedFiles":[{"fileName":"mailroom_10.3.45_darwin_amd64.tar.gz","algo":"Sha256","source":"mailroom_10.3.45_checksums.txt","hash":"9c41e91d06a8d7e9aedc04feca9a19d2833f7dd2650a91f60769aff9ecef6ff8"},{"fileName":"mailroom_10.3.45_darwin_arm64.tar.gz","algo":"Sha256","source":"mailroom_10.3.45_checksums.txt","hash":"e3202e91d94b5be2e1e34ce67086794b8876485741db347f12974d16939ede29"},{"fileName":"mailroom_10.3.45_linux_amd64.tar.gz","algo":"Sha256","source":"mailroom_10.3.45_checksums.txt","hash":"ae682ebde8cd13554bb0323ef8afbd9cbc60fa7a9f913343338da2ee2c6ce865"},{"fileName":"mailroom_10.3.45_linux_arm64.tar.gz","algo":"Sha256","source":"mailroom_10.3.45_checksums.txt","hash":"6b2db6381be64fe2e0dc514c3a6c100fc51b4661f0cd042ec0eae32172d1ef0a"}]}