{"mirroredOn":"2025-07-28T18:07:06.1439262+00:00","publishedOn":"2025-07-28T18:05:43+00:00","version":1,"publishedFiles":[{"fileName":"terraform-provider-metalcloud_7.0.1_darwin_amd64.zip","algo":"Sha256","source":"terraform-provider-metalcloud_7.0.1_SHA256SUMS","hash":"c32a1a3599fd588635b5e2beeeed2536f23baaee35b34d800f8e73bb0f7d9fbf"},{"fileName":"terraform-provider-metalcloud_7.0.1_darwin_arm64.zip","algo":"Sha256","source":"terraform-provider-metalcloud_7.0.1_SHA256SUMS","hash":"e0311d93b1109f01cf9e6e3c443a2ac4503bfd2a4076ca4fb8264aac18e602da"},{"fileName":"terraform-provider-metalcloud_7.0.1_linux_386.zip","algo":"Sha256","source":"terraform-provider-metalcloud_7.0.1_SHA256SUMS","hash":"cc15d9663295327d6494b47cfb2afffda1e2f2dddcdb0185649c33ab191b0a60"},{"fileName":"terraform-provider-metalcloud_7.0.1_linux_amd64.zip","algo":"Sha256","source":"terraform-provider-metalcloud_7.0.1_SHA256SUMS","hash":"662db126636d45668790e079857fbecc3c920da9c478477fbcc9114b2a9194e2"},{"fileName":"terraform-provider-metalcloud_7.0.1_linux_arm.zip","algo":"Sha256","source":"terraform-provider-metalcloud_7.0.1_SHA256SUMS","hash":"d005592759cad0faa55e576891addc02a71cff4f9f748b28e440829c28e97cf4"},{"fileName":"terraform-provider-metalcloud_7.0.1_linux_arm64.zip","algo":"Sha256","source":"terraform-provider-metalcloud_7.0.1_SHA256SUMS","hash":"2ed8bbc5fdfb629a12783ffcf6664ad9867e1a1896df2f64567f1215ecd20bca"},{"fileName":"terraform-provider-metalcloud_7.0.1_windows_386.zip","algo":"Sha256","source":"terraform-provider-metalcloud_7.0.1_SHA256SUMS","hash":"3a10058eb8f9f7d5d68ba64ea563076e28d9a8404b57f0aa856915e0ec5666bf"},{"fileName":"terraform-provider-metalcloud_7.0.1_windows_amd64.zip","algo":"Sha256","source":"terraform-provider-metalcloud_7.0.1_SHA256SUMS","hash":"ac41d04b885713ec61a819c5e6c8d834d6f722f3bdaa721e7fb73d9f22c5df68"},{"fileName":"terraform-provider-metalcloud_7.0.1_windows_arm.zip","algo":"Sha256","source":"terraform-provider-metalcloud_7.0.1_SHA256SUMS","hash":"dfceba2dc635112918070f424cdc0fb5ae8bf53c953ab868662de4e8f77f5dff"},{"fileName":"terraform-provider-metalcloud_7.0.1_windows_arm64.zip","algo":"Sha256","source":"terraform-provider-metalcloud_7.0.1_SHA256SUMS","hash":"ba659c10cdde488cf1dc6b87a5599699210fb3b9270238cad9f1115c212145ad"}]}