{"mirroredOn":"2025-08-01T10:10:28.2576577+00:00","publishedOn":"2025-08-01T10:08:42+00:00","version":1,"publishedFiles":[{"fileName":"./pulumi-resource-scaleway-v1.32.0-darwin-amd64.tar.gz","algo":"Sha1","source":"pulumi-scaleway_1.32.0_checksums.txt","hash":"2cc91b36b08799e8b13a16b42478769aa32d0242"},{"fileName":"./pulumi-resource-scaleway-v1.32.0-darwin-arm64.tar.gz","algo":"Sha1","source":"pulumi-scaleway_1.32.0_checksums.txt","hash":"6099c898555666de7d91909e66bdef8c261b0636"},{"fileName":"./pulumi-resource-scaleway-v1.32.0-linux-amd64.tar.gz","algo":"Sha1","source":"pulumi-scaleway_1.32.0_checksums.txt","hash":"ce6c4fd4d6802bfd518c4994288c1335b01598cb"},{"fileName":"./pulumi-resource-scaleway-v1.32.0-linux-arm64.tar.gz","algo":"Sha1","source":"pulumi-scaleway_1.32.0_checksums.txt","hash":"24e63032c32afc26d4c7d9862539e6a3c536cda3"},{"fileName":"./pulumi-resource-scaleway-v1.32.0-windows-amd64.tar.gz","algo":"Sha1","source":"pulumi-scaleway_1.32.0_checksums.txt","hash":"34b23fdf2557367e880cc3d4e9e142f7be73bef2"}]}