{"mirroredOn":"2024-11-08T13:29:21.681588+00:00","publishedOn":"2024-11-05T09:03:24+00:00","version":1,"publishedFiles":[{"fileName":"linksym_0.1.0_linux_amd64.deb","algo":"Sha256","source":"linksym_0.1.0_checksums.txt","hash":"6545ca7dbddad0b1c15a1f032455ce86e9b4f40e723f84339ef19a65da7063a5"},{"fileName":"linksym_0.1.0_linux_amd64.rpm","algo":"Sha256","source":"linksym_0.1.0_checksums.txt","hash":"f4945e3283be39f97a7439169088c42b11436b53029b57f2cee5647290f606c7"},{"fileName":"linksym_Linux_x86_64.tar.gz","algo":"Sha256","source":"linksym_0.1.0_checksums.txt","hash":"223ac4819de86a69fec371b1aaa69de97e466e185abd2689d1edb3c16fe2eb94"}]}