{"mirroredOn":"2025-04-10T02:10:08.4348448+00:00","publishedOn":"2025-04-10T02:08:44+00:00","version":1,"publishedFiles":[{"fileName":"portola-staging_Darwin_arm64.tar.gz","algo":"Sha256","source":"portola-staging_0.7.146_checksums.txt","hash":"cabf642966f421fd05bc593f8e270f09dc25bc9c373248a11ecda1115e99bace"},{"fileName":"portola-staging_Darwin_x86_64.tar.gz","algo":"Sha256","source":"portola-staging_0.7.146_checksums.txt","hash":"265ef49ea2290239e28f4674753d3abda0e81b8b25b4a0b2bdb817004c4d7454"}]}