{"mirroredOn":"2025-04-01T15:11:53.245661+00:00","publishedOn":"2025-04-01T15:10:37+00:00","version":1,"publishedFiles":[{"fileName":"inputplumber-0.50.0-1.x86_64.rpm","algo":"Sha256","source":"inputplumber-0.50.0-1.x86_64.rpm.sha256.txt","hash":"99373ae05535c68b52937002d4e6bb3e5e66041bdfa40defdc1b0e43b708abcd"},{"fileName":"inputplumber.tar.gz","algo":"Sha256","source":"inputplumber.tar.gz.sha256.txt","hash":"1defb1011945689600e6c46f3b0ad71bbc6b9ca78a60e5962d121df6d43f1ad1"},{"fileName":"inputplumber.raw","algo":"Sha256","source":"inputplumber.raw.sha256.txt","hash":"6f90ba5a25965925f231cf395f136e274a7c9a1104f33bf9e14fd2e23e5b480c"}]}