{
  "mirroredOn": null,
  "publishedOn": null,
  "version": 1,
  "publishedFiles": [
    {
      "fileName": "org.wabarc.wayback-0.20.1.x86_64.flatpak",
      "algo": "Sha256",
      "source": "wayback-0.20.1-checksums.txt",
      "hash": "895a7313f8a887f637c50c08673c8b9674c62893c7b1fe80037dfb4c95e265c0"
    },
    {
      "fileName": "wayback-0.20.1-1-x86_64.pkg.tar.zst",
      "algo": "Sha256",
      "source": "wayback-0.20.1-checksums.txt",
      "hash": "7c97c158705b753107e0b8f9bc0cd82007c9f23c549a3a30b4f3eca2821e9e46"
    },
    {
      "fileName": "wayback-0.20.1-1.0.x86_64.rpm",
      "algo": "Sha256",
      "source": "wayback-0.20.1-checksums.txt",
      "hash": "f9f1476c7f207aa7a7a10cb97211470533127dc51239dc17281a68fe55bb56b2"
    },
    {
      "fileName": "wayback-android-arm64-0.20.1.tar.gz",
      "algo": "Sha256",
      "source": "wayback-0.20.1-checksums.txt",
      "hash": "6479034717fdfa19825d74733c8930eccd2a7fc90b38a2f7157d1200dcf6df75"
    },
    {
      "fileName": "wayback-darwin-amd64-0.20.1.tar.gz",
      "algo": "Sha256",
      "source": "wayback-0.20.1-checksums.txt",
      "hash": "48cadc9e684389b6e1473d9884d1aa86edea69e189e786a6a5a4c56ebf64ea9e"
    },
    {
      "fileName": "wayback-darwin-arm64-0.20.1.tar.gz",
      "algo": "Sha256",
      "source": "wayback-0.20.1-checksums.txt",
      "hash": "0fc509d4ddcdd547b68fff82aeb4b5063d06b09b39bf23f7e3d70bf5a1ced002"
    },
    {
      "fileName": "wayback-debug-0.20.1-1-x86_64.pkg.tar.zst",
      "algo": "Sha256",
      "source": "wayback-0.20.1-checksums.txt",
      "hash": "9c8646b5232c5a1770faef8554e34a79f45669492742d5d3225219d7da3a93d5"
    },
    {
      "fileName": "wayback-dragonfly-amd64-0.20.1.tar.gz",
      "algo": "Sha256",
      "source": "wayback-0.20.1-checksums.txt",
      "hash": "9a68d4abada64830633c21007fbd3fad56b91efdd2e489b49a31255172abfa59"
    },
    {
      "fileName": "wayback-freebsd-386-0.20.1.tar.gz",
      "algo": "Sha256",
      "source": "wayback-0.20.1-checksums.txt",
      "hash": "92eaad7a78b4f0899c525a0010fceb6045a0ddbee1fcd90ee8c2c65b3be828c0"
    },
    {
      "fileName": "wayback-freebsd-amd64-0.20.1.tar.gz",
      "algo": "Sha256",
      "source": "wayback-0.20.1-checksums.txt",
      "hash": "c3a6f056ea2754e413f812f53448a174b56827392640a9a8a37d95b9b1fb3b57"
    },
    {
      "fileName": "wayback-freebsd-arm64-0.20.1.tar.gz",
      "algo": "Sha256",
      "source": "wayback-0.20.1-checksums.txt",
      "hash": "c54f950bad2be78535362c19944571346933fd717dd66ec1c42c508fcca36ece"
    },
    {
      "fileName": "wayback-linux-386-0.20.1.tar.gz",
      "algo": "Sha256",
      "source": "wayback-0.20.1-checksums.txt",
      "hash": "13f6747f930373b651425585c563655c353f1101f489f4b6290c1be0c3b2e236"
    },
    {
      "fileName": "wayback-linux-amd64-0.20.1.tar.gz",
      "algo": "Sha256",
      "source": "wayback-0.20.1-checksums.txt",
      "hash": "e7b1cbe54cc13199724d1777fd6d2d88e6d662b355625c1a18aa1653215e97d9"
    },
    {
      "fileName": "wayback-linux-arm64-0.20.1.tar.gz",
      "algo": "Sha256",
      "source": "wayback-0.20.1-checksums.txt",
      "hash": "c451986fa70bcd8b3b6860372ae27165d91de26ac17dfc57282c2557f5f0fb97"
    },
    {
      "fileName": "wayback-linux-armv5-0.20.1.tar.gz",
      "algo": "Sha256",
      "source": "wayback-0.20.1-checksums.txt",
      "hash": "26446720904b2bd98e64b4f0b5d71941fdc968c2745cf0b0575761b3633e37b4"
    },
    {
      "fileName": "wayback-linux-armv6-0.20.1.tar.gz",
      "algo": "Sha256",
      "source": "wayback-0.20.1-checksums.txt",
      "hash": "be18a7056c18378b7193aaaa7dd26319a79ec340f670b16f23fe92ea1e8086a1"
    },
    {
      "fileName": "wayback-linux-armv7-0.20.1.tar.gz",
      "algo": "Sha256",
      "source": "wayback-0.20.1-checksums.txt",
      "hash": "45c1b6535ec539f365bb405e184425207c8b4457a85911921b289188895dec0f"
    },
    {
      "fileName": "wayback-linux-mips-hardfloat-0.20.1.tar.gz",
      "algo": "Sha256",
      "source": "wayback-0.20.1-checksums.txt",
      "hash": "f2c57b0f616a83af17d069b9ee860a9a7c85717d9559ad91e47c08ab6303e263"
    },
    {
      "fileName": "wayback-linux-mips-softfloat-0.20.1.tar.gz",
      "algo": "Sha256",
      "source": "wayback-0.20.1-checksums.txt",
      "hash": "07b30b8f4eac2bd47cb5af1fa3d33c1d2b6dbad69fff84fc98000eda56907ffc"
    },
    {
      "fileName": "wayback-linux-mips64-0.20.1.tar.gz",
      "algo": "Sha256",
      "source": "wayback-0.20.1-checksums.txt",
      "hash": "c86fe71bf1075d4095a67de029fac785e856d7382c24ca94855674a06b53ce78"
    },
    {
      "fileName": "wayback-linux-mips64le-0.20.1.tar.gz",
      "algo": "Sha256",
      "source": "wayback-0.20.1-checksums.txt",
      "hash": "8e6061bfcfd3b90a7e5a43d8661552b4d57535deaa98ab73e4cba6385fb112c4"
    },
    {
      "fileName": "wayback-linux-mipsle-hardfloat-0.20.1.tar.gz",
      "algo": "Sha256",
      "source": "wayback-0.20.1-checksums.txt",
      "hash": "7829fb01a444baa27d3f5590039f604ed12656030104a3a16854753112b3ea0b"
    },
    {
      "fileName": "wayback-linux-mipsle-softfloat-0.20.1.tar.gz",
      "algo": "Sha256",
      "source": "wayback-0.20.1-checksums.txt",
      "hash": "da46e26387c671d2f42a5de2927f453022a2f3d3d065df360d971939d0ce0e29"
    },
    {
      "fileName": "wayback-linux-ppc64-0.20.1.tar.gz",
      "algo": "Sha256",
      "source": "wayback-0.20.1-checksums.txt",
      "hash": "c84f2cb59de562cebba20f0bf4c05daeefdc3fb7f745bd3a4ff2a7c73b646efa"
    },
    {
      "fileName": "wayback-linux-ppc64le-0.20.1.tar.gz",
      "algo": "Sha256",
      "source": "wayback-0.20.1-checksums.txt",
      "hash": "618682c86a755f1462f4bc14f99d55018e452fb304df8cb43d200bd610f351fc"
    },
    {
      "fileName": "wayback-linux-s390x-0.20.1.tar.gz",
      "algo": "Sha256",
      "source": "wayback-0.20.1-checksums.txt",
      "hash": "4f36f525effb3b6d408a0fd1bb924977f221b6ebe5ae8f39201a267256d4a733"
    },
    {
      "fileName": "wayback-openbsd-386-0.20.1.tar.gz",
      "algo": "Sha256",
      "source": "wayback-0.20.1-checksums.txt",
      "hash": "a75f521a7d4acb5431035015daa106df5051a9eb1ebbefaa081d6fdbd82e9413"
    },
    {
      "fileName": "wayback-openbsd-amd64-0.20.1.tar.gz",
      "algo": "Sha256",
      "source": "wayback-0.20.1-checksums.txt",
      "hash": "2621f01701bb803bc0a2bc393165ec8b3ee42f681bc3b1803e102fca5dfa898f"
    },
    {
      "fileName": "wayback-windows-386-0.20.1.zip",
      "algo": "Sha256",
      "source": "wayback-0.20.1-checksums.txt",
      "hash": "4ac4ad4d3a91666a3512e845838e47e618f1065fb5849e25f1607995c87d99d4"
    },
    {
      "fileName": "wayback-windows-amd64-0.20.1.zip",
      "algo": "Sha256",
      "source": "wayback-0.20.1-checksums.txt",
      "hash": "28d814af1c60da2a2cbeed2ca85d61ffe861e59d0b58b4ab58d350b6fe854df6"
    },
    {
      "fileName": "wayback-windows-arm-0.20.1.zip",
      "algo": "Sha256",
      "source": "wayback-0.20.1-checksums.txt",
      "hash": "3a886886adb4a4c36510547be5df06d2e26138f613a81b9092e01ef90a08def5"
    },
    {
      "fileName": "wayback-windows-arm64-0.20.1.zip",
      "algo": "Sha256",
      "source": "wayback-0.20.1-checksums.txt",
      "hash": "10c9ae713dcb2e2989edabe2613a178da248c4be89c2b9786af30f41c10874e8"
    },
    {
      "fileName": "wayback_0.20.1_amd64.deb",
      "algo": "Sha256",
      "source": "wayback-0.20.1-checksums.txt",
      "hash": "08da515c106f51be8b4069f48b85bca5aaee544ea5610a4c31a0ed9aed1f96c9"
    },
    {
      "fileName": "wayback_0.20.1_arm64.deb",
      "algo": "Sha256",
      "source": "wayback-0.20.1-checksums.txt",
      "hash": "7b39e879fe35cdb5adc75313a58fbc69cb345a7ae4e5662485d1ff51d2aaf00f"
    },
    {
      "fileName": "wayback_0.20.1_armhf.deb",
      "algo": "Sha256",
      "source": "wayback-0.20.1-checksums.txt",
      "hash": "66a09da89fc195b3d2ad8cdf0994bf2554abab1049483b4a53b8efc333433bb5"
    },
    {
      "fileName": "wayback_0.20.1_multi.snap",
      "algo": "Sha256",
      "source": "wayback-0.20.1-checksums.txt",
      "hash": "753d36b8ccc0a619d13fef7552d3464ba079d7775aec19e7cfdc360b8a4285f3"
    }
  ]
}