{"mirroredOn":"2026-02-20T04:17:15.4037985+00:00","publishedOn":"2026-02-20T04:14:43+00:00","version":1,"publishedFiles":[{"fileName":"./pulumi-resource-auth0-v3.38.0-darwin-amd64.tar.gz","algo":"Sha1","source":"pulumi-auth0_3.38.0_checksums.txt","hash":"5332bdbabb34b7232dad19b712ace61e774bf899"},{"fileName":"./pulumi-resource-auth0-v3.38.0-darwin-arm64.tar.gz","algo":"Sha1","source":"pulumi-auth0_3.38.0_checksums.txt","hash":"c10b1ee3beae211cde514477fc8a95babfb71590"},{"fileName":"./pulumi-resource-auth0-v3.38.0-linux-amd64.tar.gz","algo":"Sha1","source":"pulumi-auth0_3.38.0_checksums.txt","hash":"2eb4a60ad17544c2df91282cf903989029a2e866"},{"fileName":"./pulumi-resource-auth0-v3.38.0-linux-arm64.tar.gz","algo":"Sha1","source":"pulumi-auth0_3.38.0_checksums.txt","hash":"1576f9b334e495a5c981a4cf64e01506e68f52c1"},{"fileName":"./pulumi-resource-auth0-v3.38.0-windows-amd64.tar.gz","algo":"Sha1","source":"pulumi-auth0_3.38.0_checksums.txt","hash":"6401924fe1139e215144f646f8b8b5cd81e0ab52"},{"fileName":"./pulumi-resource-auth0-v3.38.0-windows-arm64.tar.gz","algo":"Sha1","source":"pulumi-auth0_3.38.0_checksums.txt","hash":"3d80f36bac892457c69eb75eb8a49417aad13a3f"}]}