{"mirroredOn":"2025-12-18T19:37:47.9367713+00:00","publishedOn":"2025-12-18T19:36:19+00:00","version":1,"publishedFiles":[{"fileName":"./pulumi-resource-xyz-v1.1.339-darwin-amd64.tar.gz","algo":"Sha1","source":"pulumi-xyz_1.1.339_checksums.txt","hash":"514739f7db61576454d8291b3fba2f4f8486cfb0"},{"fileName":"./pulumi-resource-xyz-v1.1.339-darwin-arm64.tar.gz","algo":"Sha1","source":"pulumi-xyz_1.1.339_checksums.txt","hash":"a5bb03e083dee6ce5cfd9e10481cb7f3dc13bbea"},{"fileName":"./pulumi-resource-xyz-v1.1.339-linux-amd64.tar.gz","algo":"Sha1","source":"pulumi-xyz_1.1.339_checksums.txt","hash":"190895c58156ebfd6932a35edbc3efb381bda61a"},{"fileName":"./pulumi-resource-xyz-v1.1.339-linux-arm64.tar.gz","algo":"Sha1","source":"pulumi-xyz_1.1.339_checksums.txt","hash":"a8de232f5107ee648f581b95ca52ac3396b4e204"},{"fileName":"./pulumi-resource-xyz-v1.1.339-windows-amd64.tar.gz","algo":"Sha1","source":"pulumi-xyz_1.1.339_checksums.txt","hash":"c0f97b5c52bda6961bc6c500b9e8c417b59411fc"},{"fileName":"./pulumi-resource-xyz-v1.1.339-windows-arm64.tar.gz","algo":"Sha1","source":"pulumi-xyz_1.1.339_checksums.txt","hash":"11b5ec73ac18a9012971d100b5f089c8db6d5b10"}]}