{"mirroredOn":"2025-05-09T18:07:54.4598559+00:00","publishedOn":"2025-05-09T18:05:34+00:00","version":1,"publishedFiles":[{"fileName":"wp-github-comment-linux-amd64","algo":"Sha256","source":"wp-github-comment-linux-amd64.sha256","hash":"0b2a26c5a8ab8c673947fa77743a2843c35a633f72af2552a5343a423b40c473"},{"fileName":"wp-github-comment-linux-arm-6","algo":"Sha256","source":"wp-github-comment-linux-arm-6.sha256","hash":"f34858b55cb73636de0f54202d94985318d7e2a805c2e3a1dae87b3278b4fa12"},{"fileName":"wp-github-comment-linux-arm64","algo":"Sha256","source":"wp-github-comment-linux-arm64.sha256","hash":"b7526e56f397315ee0cd5043d20ff1f1e3034b9d5ff318c018955a2f1eb58b7e"},{"fileName":"wp-github-comment-linux-arm-7","algo":"Sha256","source":"wp-github-comment-linux-arm-7.sha256","hash":"f974321cf6e6c8fa525d34cbbb40425c4e391ad1fb6447cb26e4d3f544be8422"}]}