{"mirroredOn":"2026-06-23T23:47:31.2913511+00:00","publishedOn":"2026-06-23T23:45:34+00:00","version":1,"publishedFiles":[{"fileName":"terraform-provider-cpln_1.2.30_darwin_amd64.zip","algo":"Sha256","source":"terraform-provider-cpln_1.2.30_SHA256SUMS","hash":"64dcca633a51f3ed060d5e81b52ed6e953e3be1d5f95db11a2d50957716bac1d"},{"fileName":"terraform-provider-cpln_1.2.30_darwin_arm64.zip","algo":"Sha256","source":"terraform-provider-cpln_1.2.30_SHA256SUMS","hash":"3ff14b4e935c5ad6175d430e54b265a93f89acdd30dfbc540f9b39e52221dfc3"},{"fileName":"terraform-provider-cpln_1.2.30_freebsd_386.zip","algo":"Sha256","source":"terraform-provider-cpln_1.2.30_SHA256SUMS","hash":"0389a8bf8aa8900d670165c11209c71365894629a23e2e57299c4300632cdcdf"},{"fileName":"terraform-provider-cpln_1.2.30_freebsd_amd64.zip","algo":"Sha256","source":"terraform-provider-cpln_1.2.30_SHA256SUMS","hash":"1ab5098c0a1388fb93f676224907b2c13dbcca491a676ca786b079ae5cae62cb"},{"fileName":"terraform-provider-cpln_1.2.30_freebsd_arm.zip","algo":"Sha256","source":"terraform-provider-cpln_1.2.30_SHA256SUMS","hash":"e568347e23e48139a686ef5b2d7859dcbe2d9c4fc64e50be0a79cf8448ad9b1c"},{"fileName":"terraform-provider-cpln_1.2.30_freebsd_arm64.zip","algo":"Sha256","source":"terraform-provider-cpln_1.2.30_SHA256SUMS","hash":"c68f69db09c3a245c19e30cb01a5407fafdcfc1c9e5da81532575e0f2bff9886"},{"fileName":"terraform-provider-cpln_1.2.30_linux_386.zip","algo":"Sha256","source":"terraform-provider-cpln_1.2.30_SHA256SUMS","hash":"74f918be9e5993c81ea1b6767c23eb2844a9bf0a29b9a3fa12d440196a0cbf43"},{"fileName":"terraform-provider-cpln_1.2.30_linux_amd64.zip","algo":"Sha256","source":"terraform-provider-cpln_1.2.30_SHA256SUMS","hash":"437975926c65ba2e268e036e30dddc5f9fed1d08b2b9df21ff28d36f813c4543"},{"fileName":"terraform-provider-cpln_1.2.30_linux_arm.zip","algo":"Sha256","source":"terraform-provider-cpln_1.2.30_SHA256SUMS","hash":"16be99ad0e703598d0c34d1b8185aa22fc1b2d167673baec675f539fa6f956ae"},{"fileName":"terraform-provider-cpln_1.2.30_linux_arm64.zip","algo":"Sha256","source":"terraform-provider-cpln_1.2.30_SHA256SUMS","hash":"7c232bb0e3e726916942f809b5d720b5e963c7184cbbd587cebca649bfc02237"},{"fileName":"terraform-provider-cpln_1.2.30_manifest.json","algo":"Sha256","source":"terraform-provider-cpln_1.2.30_SHA256SUMS","hash":"f809ab383cca0a5f83072981c64208cbd7fa67e986a86ee02dd2c82333221e32"},{"fileName":"terraform-provider-cpln_1.2.30_windows_386.zip","algo":"Sha256","source":"terraform-provider-cpln_1.2.30_SHA256SUMS","hash":"cd7753e803a9ebe3e69df03551890140eb8ef9cf5cda8c4e54cf4c1e0e5be9f4"},{"fileName":"terraform-provider-cpln_1.2.30_windows_amd64.zip","algo":"Sha256","source":"terraform-provider-cpln_1.2.30_SHA256SUMS","hash":"8d8d1b474f03b67c12b8a15a86e6eae1bcc6b3a0bea72c0b80c8ccacb06e8e28"},{"fileName":"terraform-provider-cpln_1.2.30_windows_arm64.zip","algo":"Sha256","source":"terraform-provider-cpln_1.2.30_SHA256SUMS","hash":"f8a377d02932bfc69547d15bfad2e02536dc1bac1b436aa5349ff7055c3a99ad"}]}