{"mirroredOn":"2026-06-01T21:14:01.8947452+00:00","publishedOn":"2026-06-01T21:09:48+00:00","version":1,"publishedFiles":[{"fileName":"mailroom_1.87.3-a0-staging_darwin_amd64.tar.gz","algo":"Sha256","source":"mailroom_1.87.3-a0-staging_checksums.txt","hash":"8a41a7559f481df6410b59a7c30508639e9f6ff4e34fe9e6c07b54b32f4f113b"},{"fileName":"mailroom_1.87.3-a0-staging_linux_amd64.tar.gz","algo":"Sha256","source":"mailroom_1.87.3-a0-staging_checksums.txt","hash":"bad228c968be3cb48e5f31fbdc36ae3a1680b09e5d49a12202b3da66a24918b0"}]}