{"mirroredOn":"2025-04-29T19:20:51.3481103+00:00","publishedOn":"2025-04-29T19:16:45+00:00","version":1,"publishedFiles":[{"fileName":"./pulumi-resource-gcp-v8.28.0-darwin-amd64.tar.gz","algo":"Sha1","source":"pulumi-gcp_8.28.0_checksums.txt","hash":"2386c497db8ed89ef79e1788211473b502d16a7b"},{"fileName":"./pulumi-resource-gcp-v8.28.0-darwin-arm64.tar.gz","algo":"Sha1","source":"pulumi-gcp_8.28.0_checksums.txt","hash":"93642b76e62e7f2d7d41c6526fbaa01be6e486cd"},{"fileName":"./pulumi-resource-gcp-v8.28.0-linux-amd64.tar.gz","algo":"Sha1","source":"pulumi-gcp_8.28.0_checksums.txt","hash":"41fddbd397a51f8cc391bf93f66b48b93da632b6"},{"fileName":"./pulumi-resource-gcp-v8.28.0-linux-arm64.tar.gz","algo":"Sha1","source":"pulumi-gcp_8.28.0_checksums.txt","hash":"480ee1bbaabe6cc11b071cb9119ab297669e03d8"},{"fileName":"./pulumi-resource-gcp-v8.28.0-windows-amd64.tar.gz","algo":"Sha1","source":"pulumi-gcp_8.28.0_checksums.txt","hash":"add0f46dae5caa69a8dd985b273e04579a111e41"}]}