{"mirroredOn":"2025-06-24T10:10:09.2859925+00:00","publishedOn":"2025-06-24T10:08:47+00:00","version":1,"publishedFiles":[{"fileName":"handwriting-keyboard-t_2.1.0_amd64.deb","algo":"Sha256","source":"handwriting-keyboard-t_2.1.0_amd64.deb.sha256","hash":"80ed308d12fc99c540a623c0ed47e62e0ed09747450a25e20a77bdf65a98e213"},{"fileName":"handwriting-keyboard-t-2.1.0-1.x86_64.rpm","algo":"Sha256","source":"handwriting-keyboard-t-2.1.0-1.x86_64.rpm.sha256","hash":"7c23e0ed94969bd300dd74c5ff0da3c011b0d14f5fb6f730f13d0fbfa9a97a81"},{"fileName":"handwriting-keyboard-t_2.1.0_amd64.AppImage","algo":"Sha256","source":"handwriting-keyboard-t_2.1.0_amd64.AppImage.sha256","hash":"bb249a2c4f0065830886469931563614513053b4b79f9e4184f77d8c2664a2cb"}]}