{"mirroredOn":"2025-09-10T03:39:50.087274+00:00","publishedOn":"2025-09-10T03:38:24+00:00","version":1,"publishedFiles":[{"fileName":"./pulumi-resource-auth0-v3.27.0-darwin-amd64.tar.gz","algo":"Sha1","source":"pulumi-auth0_3.27.0_checksums.txt","hash":"a2507d2249dfc6e0efd772a232d5c8b0c05d4c66"},{"fileName":"./pulumi-resource-auth0-v3.27.0-darwin-arm64.tar.gz","algo":"Sha1","source":"pulumi-auth0_3.27.0_checksums.txt","hash":"491fb15a6b51197f6fc29c1633684fce08030441"},{"fileName":"./pulumi-resource-auth0-v3.27.0-linux-amd64.tar.gz","algo":"Sha1","source":"pulumi-auth0_3.27.0_checksums.txt","hash":"b523552a3553875afa982735e0c3d3b560bf434f"},{"fileName":"./pulumi-resource-auth0-v3.27.0-linux-arm64.tar.gz","algo":"Sha1","source":"pulumi-auth0_3.27.0_checksums.txt","hash":"7ebc4dc29422c3d6ba4cbe1faf78e396438ebb0a"},{"fileName":"./pulumi-resource-auth0-v3.27.0-windows-amd64.tar.gz","algo":"Sha1","source":"pulumi-auth0_3.27.0_checksums.txt","hash":"594d35b79111e46e5a127d544612e4ab7d9e6b1a"},{"fileName":"./pulumi-resource-auth0-v3.27.0-windows-arm64.tar.gz","algo":"Sha1","source":"pulumi-auth0_3.27.0_checksums.txt","hash":"a7dd471092a730eca171c387a271d70baeee8403"}]}