{"mirroredOn":"2024-12-29T09:19:22.6124954+00:00","publishedOn":"2024-12-29T07:20:56+00:00","version":1,"publishedFiles":[{"fileName":"idpbuilder-darwin-v0.7.0-nightly.20241229-amd64.tar.gz","algo":"Sha256","source":"checksums.txt","hash":"2a22695b060f9a2156587e5018147ef5d40dfeae8e23813667222b7e48bb553c"},{"fileName":"idpbuilder-darwin-v0.7.0-nightly.20241229-arm64.tar.gz","algo":"Sha256","source":"checksums.txt","hash":"f29c5c5be8dcf7479f8347618aa63acaf8c779264475886542c13af4035884b9"},{"fileName":"idpbuilder-linux-v0.7.0-nightly.20241229-amd64.tar.gz","algo":"Sha256","source":"checksums.txt","hash":"be6944ebb2bf91131a0c8f09b2d621f0450d873858fff0728673ee481eb13cde"},{"fileName":"idpbuilder-linux-v0.7.0-nightly.20241229-arm64.tar.gz","algo":"Sha256","source":"checksums.txt","hash":"b3c1d6c463ae74abe4d26e4171009f4cf6bfd8f2c4bb22738f87d7c6cc3c0eaa"}]}