{"mirroredOn":"2025-02-22T01:50:29.8032903+00:00","publishedOn":"2025-02-10T09:48:36+00:00","version":1,"publishedFiles":[{"fileName":"Burrow_1.9.2_darwin_amd64.tar.gz","algo":"Sha256","source":"Burrow_1.9.2_checksums.txt","hash":"dd1d14429916cad8564bfa1091a1e4308e9bc50bcd8f29c535254e606a906345"},{"fileName":"Burrow_1.9.2_linux_amd64.tar.gz","algo":"Sha256","source":"Burrow_1.9.2_checksums.txt","hash":"85e005b22612a1cec9a108ba6c3e0c6fef3f6c0105d6d2e9fdf1984b77a61a5f"},{"fileName":"Burrow_1.9.2_windows_amd64.tar.gz","algo":"Sha256","source":"Burrow_1.9.2_checksums.txt","hash":"7bbc3a3f74b48020b4476270534d76e2b5d764cee41c9d748dc16c03a1226a5b"}]}