{"mirroredOn":"2025-04-11T15:05:32.144089+00:00","publishedOn":"2025-04-11T15:04:16+00:00","version":1,"publishedFiles":[{"fileName":"terraform-provider-lumen_2.6.0_darwin_amd64.zip","algo":"Sha256","source":"terraform-provider-lumen_2.6.0_SHA256SUMS","hash":"5c3535fd5c7e077820f4f0931686fce8577e9bf7f6bb3248a6acf532174fda0d"},{"fileName":"terraform-provider-lumen_2.6.0_darwin_arm64.zip","algo":"Sha256","source":"terraform-provider-lumen_2.6.0_SHA256SUMS","hash":"c0153a09cc053e673a46fe4f025c17defa2a5bf9a637697ea4260a462d3309c2"},{"fileName":"terraform-provider-lumen_2.6.0_freebsd_386.zip","algo":"Sha256","source":"terraform-provider-lumen_2.6.0_SHA256SUMS","hash":"7fd44905a0b3a97355fc6ab1b764df6f39d5b9db8965fbcd70db2302b6930409"},{"fileName":"terraform-provider-lumen_2.6.0_freebsd_amd64.zip","algo":"Sha256","source":"terraform-provider-lumen_2.6.0_SHA256SUMS","hash":"79b99e6e0a73469622f7e1c10cf9455c310af6bf2a9419c96994169df7431182"},{"fileName":"terraform-provider-lumen_2.6.0_freebsd_arm.zip","algo":"Sha256","source":"terraform-provider-lumen_2.6.0_SHA256SUMS","hash":"050b5c396cb45cb374e317a59db36d8a369746284b7ee41d0cbcff7e34ce282f"},{"fileName":"terraform-provider-lumen_2.6.0_freebsd_arm64.zip","algo":"Sha256","source":"terraform-provider-lumen_2.6.0_SHA256SUMS","hash":"072447c6331b11516eb37de58890f0fe3dcdd9f9c8c7aabfc9ff7dd51ef87044"},{"fileName":"terraform-provider-lumen_2.6.0_linux_386.zip","algo":"Sha256","source":"terraform-provider-lumen_2.6.0_SHA256SUMS","hash":"f6066b73083374277f3a82fb05f4fee87c0ed37d92f56df33dfd06185d548d0d"},{"fileName":"terraform-provider-lumen_2.6.0_linux_amd64.zip","algo":"Sha256","source":"terraform-provider-lumen_2.6.0_SHA256SUMS","hash":"18f778391d959a657940d396a3c18fc3d9e6f8a7574b51055eb8ea1d4c6b50c8"},{"fileName":"terraform-provider-lumen_2.6.0_linux_arm.zip","algo":"Sha256","source":"terraform-provider-lumen_2.6.0_SHA256SUMS","hash":"81bc9eab3a9ba5c5d5f837417b08df4a780bf122627acf15ff17161982a25ac9"},{"fileName":"terraform-provider-lumen_2.6.0_linux_arm64.zip","algo":"Sha256","source":"terraform-provider-lumen_2.6.0_SHA256SUMS","hash":"fce485c05cc2829302cf40450231ce8323ed9b66c352a6bdd96da7520e093a73"},{"fileName":"terraform-provider-lumen_2.6.0_manifest.json","algo":"Sha256","source":"terraform-provider-lumen_2.6.0_SHA256SUMS","hash":"9b3ac9b1f2478156d54fd8dd9bb596a51429eae0bdf39ee4de6521c1ca002c4a"},{"fileName":"terraform-provider-lumen_2.6.0_windows_386.zip","algo":"Sha256","source":"terraform-provider-lumen_2.6.0_SHA256SUMS","hash":"101c408ffbc13158a5a5a400e7ef00153832559530c8ccfb44146883f7094d45"},{"fileName":"terraform-provider-lumen_2.6.0_windows_amd64.zip","algo":"Sha256","source":"terraform-provider-lumen_2.6.0_SHA256SUMS","hash":"9c688cf90a21d98d0c881bff9b6b7972b39d52fbe3c30f8481cf0057da75f5de"},{"fileName":"terraform-provider-lumen_2.6.0_windows_arm.zip","algo":"Sha256","source":"terraform-provider-lumen_2.6.0_SHA256SUMS","hash":"cb88a42d45d67001cea93821aa48eac05b32e45869373d75387bb825ca107f14"}]}