{"mirroredOn":"2025-08-30T19:04:12.3905734+00:00","publishedOn":"2025-08-30T19:02:26+00:00","version":1,"publishedFiles":[{"fileName":"acars-processor-v1.0.2-linux-386","algo":"Sha256","source":"acars-processor-v1.0.2-linux-386.sha256","hash":"6b1438ce005916f6db8c905d62b728b059827df5316199ea58ee6547413e45a4"},{"fileName":"acars-processor-v1.0.2-linux-arm64","algo":"Sha256","source":"acars-processor-v1.0.2-linux-arm64.sha256","hash":"3a6e1d992b108e356253e93459afca85d4e9d704fed35ccb3a47d0c55565898f"},{"fileName":"acars-processor-v1.0.2-darwin-arm64","algo":"Sha256","source":"acars-processor-v1.0.2-darwin-arm64.sha256","hash":"6712fed7f831323525dd8e2b1c544bb080617b7cf07c4c5ca31f8a2418e20bb3"},{"fileName":"acars-processor-v1.0.2-darwin-amd64","algo":"Sha256","source":"acars-processor-v1.0.2-darwin-amd64.sha256","hash":"1a820ef649331b78848c66484b8910bdbbc8ed1dcc23d332627bfe3fde8c682b"}]}